pydbus_objectmanager/__init__.py
pydbus_objectmanager/proxy.py
pydbus_objectmanager/publication.py
pydbus_objectmanager/registration.py
pydbus_objectmanager/subscription.py
pydbus_objectmanager-0.1.dist-info/LICENSE
pydbus_objectmanager-0.1.dist-info/METADATA
pydbus_objectmanager-0.1.dist-info/WHEEL
pydbus_objectmanager-0.1.dist-info/top_level.txt
pydbus_objectmanager-0.1.dist-info/RECORD
