Metadata-Version: 2.1
Name: pydbus-objectmanager
Version: 0.1
Summary: DBus.ObjectManager implementation for pydbus
Home-page: https://github.com/milindur/pydbus-objectmanager
Author: Christian Andersen
Author-email: christian@milindur.de
License: WTFPL
License-File: LICENSE
Requires-Dist: pydbus (>=0.6)
